__init__.py
pytest_better_parametrize/__init__.py
pytest_better_parametrize/core.py
pytest_better_parametrize/plugin.py
pytest_better_parametrize-0.2.0.dist-info/LICENSE
pytest_better_parametrize-0.2.0.dist-info/METADATA
pytest_better_parametrize-0.2.0.dist-info/WHEEL
pytest_better_parametrize-0.2.0.dist-info/entry_points.txt
pytest_better_parametrize-0.2.0.dist-info/top_level.txt
pytest_better_parametrize-0.2.0.dist-info/RECORD
